README.rst
setup.cfg
setup.py
bouncer/__init__.py
bouncer/constants.py
bouncer/exceptions.py
bouncer/models.py
bouncer.egg-info/PKG-INFO
bouncer.egg-info/SOURCES.txt
bouncer.egg-info/dependency_links.txt
bouncer.egg-info/not-zip-safe
bouncer.egg-info/top_level.txt