Metadata-Version: 1.0
Name: bouncer
Version: 0.1.12
Summary: Simple Declarative Authentication based on Ryan Bates excellent cancan library
Home-page: http://github.com/jtushman/bouncer
Author: Jonathan Tushman
Author-email: jonathan@zefr.com
License: MIT
Platform: UNKNOWN
